{
  "books": [
    {
      "id": "f8cca2e7-1d17-4f1b-b60a-a61177443d30",
      "title": "The Great Gatsby",
      "author": "F. Scott Fitzgerald",
      "price": 299,
      "originalPrice": 499,
      "category": "Fiction",
      "rating": 4.5,
      "reviews": 2847,
      "stock": 50,
      "description": "A story of decadence, idealism, and the American Dream set in the Jazz Age.",
      "coverColor": "#1a1a2e",
      "coverAccent": "#e94560",
      "coverImage": "https://covers.openlibrary.org/b/isbn/9780743273565-L.jpg",
      "badge": "Bestseller",
      "featured": true,
      "createdAt": "2026-03-26T17:43:04.122Z"
    },
    {
      "id": "4356df0a-9698-44b9-9e58-a5744a6d9168",
      "title": "To Kill a Mockingbird",
      "author": "Harper Lee",
      "price": 349,
      "originalPrice": 599,
      "category": "Fiction",
      "rating": 4.8,
      "reviews": 5921,
      "stock": 35,
      "description": "A Pulitzer Prize-winning masterwork of honor and injustice in the deep South.",
      "coverColor": "#0f3460",
      "coverAccent": "#e2b04a",
      "coverImage": "https://covers.openlibrary.org/b/isbn/9780061935466-L.jpg",
      "badge": "Award Winner",
      "featured": true,
      "createdAt": "2026-03-26T17:43:04.122Z"
    },
    {
      "id": "caee95d2-187d-4148-98d3-831d4d5bac94",
      "title": "1984",
      "author": "George Orwell",
      "price": 249,
      "originalPrice": 399,
      "category": "Dystopian",
      "rating": 4.7,
      "reviews": 8103,
      "stock": 60,
      "description": "A dystopian social science fiction novel and cautionary tale about totalitarianism.",
      "coverColor": "#16213e",
      "coverAccent": "#c84b31",
      "coverImage": "https://covers.openlibrary.org/b/isbn/9780451524935-L.jpg",
      "badge": "Classic",
      "featured": true,
      "createdAt": "2026-03-26T17:43:04.122Z"
    },
    {
      "id": "ea6c5cc5-4f7b-416c-be8e-109e64c94f85",
      "title": "Atomic Habits",
      "author": "James Clear",
      "price": 499,
      "originalPrice": 799,
      "category": "Self-Help",
      "rating": 4.9,
      "reviews": 12450,
      "stock": 80,
      "description": "An easy and proven way to build good habits and break bad ones.",
      "coverColor": "#1b4332",
      "coverAccent": "#f4d03f",
      "coverImage": "https://covers.openlibrary.org/b/isbn/9780735211292-L.jpg",
      "badge": "#1 Bestseller",
      "featured": true,
      "createdAt": "2026-03-26T17:43:04.122Z"
    },
    {
      "id": "65ddb3b0-801c-4eca-b75c-17e99fe514e4",
      "title": "Sapiens",
      "author": "Yuval Noah Harari",
      "price": 449,
      "originalPrice": 699,
      "category": "History",
      "rating": 4.6,
      "reviews": 9234,
      "stock": 45,
      "description": "A brief history of humankind from the Stone Age to the Silicon Age.",
      "coverColor": "#2d1b69",
      "coverAccent": "#f39c12",
      "coverImage": "https://covers.openlibrary.org/b/isbn/9780062316097-L.jpg",
      "badge": "Trending",
      "featured": false,
      "createdAt": "2026-03-26T17:43:04.122Z"
    },
    {
      "id": "5b885bbf-65de-4e2f-bf72-62c45c6ef45f",
      "title": "The Psychology of Money",
      "author": "Morgan Housel",
      "price": 399,
      "originalPrice": 599,
      "category": "Finance",
      "rating": 4.7,
      "reviews": 7856,
      "stock": 55,
      "description": "Timeless lessons on wealth, greed, and happiness.",
      "coverColor": "#1a3a4a",
      "coverAccent": "#27ae60",
      "coverImage": "https://covers.openlibrary.org/b/isbn/9780857197689-L.jpg",
      "badge": "New",
      "featured": false,
      "createdAt": "2026-03-26T17:43:04.122Z"
    },
    {
      "id": "b50bb222-9026-4fc6-910e-2985888a3bef",
      "title": "Dune",
      "author": "Frank Herbert",
      "price": 549,
      "originalPrice": 899,
      "category": "Sci-Fi",
      "rating": 4.8,
      "reviews": 6721,
      "stock": 30,
      "description": "Set in the distant future amidst a feudal interstellar society.",
      "coverColor": "#3d2b1f",
      "coverAccent": "#e67e22",
      "coverImage": "https://covers.openlibrary.org/b/isbn/9780441013593-L.jpg",
      "badge": "Epic",
      "featured": false,
      "createdAt": "2026-03-26T17:43:04.122Z"
    },
    {
      "id": "7b48854f-4a29-4063-ae49-5758ac754ab6",
      "title": "The Midnight Library",
      "author": "Matt Haig",
      "price": 329,
      "originalPrice": 499,
      "category": "Fiction",
      "rating": 4.4,
      "reviews": 4523,
      "stock": 40,
      "description": "Between life and death there is a library where every book is a life you could have lived.",
      "coverColor": "#0d2137",
      "coverAccent": "#3498db",
      "coverImage": "https://covers.openlibrary.org/b/isbn/9780525559474-L.jpg",
      "badge": "Staff Pick",
      "featured": false,
      "createdAt": "2026-03-26T17:43:04.122Z"
    },
    {
      "id": "a03e587b-8da4-4967-9a26-097836d5e662",
      "title": "Thinking, Fast and Slow",
      "author": "Daniel Kahneman",
      "price": 459,
      "originalPrice": 699,
      "category": "Psychology",
      "rating": 4.6,
      "reviews": 8902,
      "stock": 25,
      "description": "A groundbreaking tour of the mind by Nobel laureate Daniel Kahneman.",
      "coverColor": "#1c1c1c",
      "coverAccent": "#e74c3c",
      "coverImage": "https://covers.openlibrary.org/b/isbn/9780374533557-L.jpg",
      "badge": "Nobel Winner",
      "featured": false,
      "createdAt": "2026-03-26T17:43:04.122Z"
    },
    {
      "id": "71d154ec-9a64-4ad2-8658-376da4837a54",
      "title": "The Alchemist",
      "author": "Paulo Coelho",
      "price": 199,
      "originalPrice": 349,
      "category": "Fiction",
      "rating": 4.5,
      "reviews": 11203,
      "stock": 70,
      "description": "A magical story about following your dreams across the Egyptian desert.",
      "coverColor": "#2c1810",
      "coverAccent": "#f1c40f",
      "coverImage": "https://covers.openlibrary.org/b/isbn/9780062315007-L.jpg",
      "badge": "All Time Classic",
      "featured": false,
      "createdAt": "2026-03-26T17:43:04.122Z"
    },
    {
      "id": "b59daa20-ca30-49f1-9fd9-e8e1efa80aaf",
      "title": "Rich Dad Poor Dad",
      "author": "Robert T. Kiyosaki",
      "price": 279,
      "originalPrice": 449,
      "category": "Finance",
      "rating": 4.3,
      "reviews": 14500,
      "stock": 90,
      "description": "What the rich teach their kids about money — the #1 personal finance book.",
      "coverColor": "#7d1d1d",
      "coverAccent": "#f39c12",
      "coverImage": "https://covers.openlibrary.org/b/isbn/9781612680194-L.jpg",
      "badge": "Iconic",
      "featured": false,
      "createdAt": "2026-03-26T17:43:04.122Z"
    },
    {
      "id": "265afbf2-c0a9-4424-b503-0ce48ff9c019",
      "title": "Brave New World",
      "author": "Aldous Huxley",
      "price": 229,
      "originalPrice": 399,
      "category": "Dystopian",
      "rating": 4.4,
      "reviews": 5603,
      "stock": 45,
      "description": "A dystopian novel set in a futuristic World State of genetically modified citizens.",
      "coverColor": "#0a2240",
      "coverAccent": "#9b59b6",
      "coverImage": "https://covers.openlibrary.org/b/isbn/9780060850524-L.jpg",
      "badge": "Classic",
      "featured": false,
      "createdAt": "2026-03-26T17:43:04.122Z"
    }
  ],
  "orders": [],
  "messages": [],
  "admins": [
    {
      "id": "fe3ae52f-d54e-411f-8d7d-9a9c0b8dc7f2",
      "username": "admin",
      "password": "$2a$10$/rQcOpycp2hgxxu6HmeMiee6Iu9/SXWF2kjwB4BCSkEcekFlheGqy",
      "name": "Admin User",
      "createdAt": "2026-03-24T06:45:12.798Z"
    }
  ],
  "users": []
}